odoo/addons/stock_valuation_layer_total_value/README.rst
odoo/addons/stock_valuation_layer_total_value/__init__.py
odoo/addons/stock_valuation_layer_total_value/__manifest__.py
odoo/addons/stock_valuation_layer_total_value/i18n/it.po
odoo/addons/stock_valuation_layer_total_value/i18n/stock_valuation_layer_total_value.pot
odoo/addons/stock_valuation_layer_total_value/models/__init__.py
odoo/addons/stock_valuation_layer_total_value/models/stock_valuation_layer.py
odoo/addons/stock_valuation_layer_total_value/readme/CONTRIBUTORS.rst
odoo/addons/stock_valuation_layer_total_value/readme/DESCRIPTION.rst
odoo/addons/stock_valuation_layer_total_value/readme/USAGE.rst
odoo/addons/stock_valuation_layer_total_value/static/description/icon.png
odoo/addons/stock_valuation_layer_total_value/static/description/index.html
odoo/addons/stock_valuation_layer_total_value/tests/__init__.py
odoo/addons/stock_valuation_layer_total_value/tests/test_stock_valuation_layer_total_value.py
odoo/addons/stock_valuation_layer_total_value/views/stock_valuation_layer.xml
odoo_addon_stock_valuation_layer_total_value-16.0.1.0.0.4.dist-info/METADATA
odoo_addon_stock_valuation_layer_total_value-16.0.1.0.0.4.dist-info/WHEEL
odoo_addon_stock_valuation_layer_total_value-16.0.1.0.0.4.dist-info/top_level.txt
odoo_addon_stock_valuation_layer_total_value-16.0.1.0.0.4.dist-info/RECORD
